{
  "2B2": "null",
  "2C2": "La société GLOBAL EXPLOITATION, Société par Actions Simplifiée Unipersonnelle",
  "2D2": "Oui, le Preneur est autorisé à sous-louer les locaux meublés objets du présent bail à tout sous-locataire exerçant les mêmes activités.",
  "2E2": "Cession du droit au bail seul autorisée avec conditions.",
  "2F2": "Cession du fonds de commerce autorisée avec conditions.",
  "2G2": "Le Preneur s'engage à rendre les lieux en bon état d'usage normal et de réparations locatives.",
  "2H2": "Avec indemnité, le Bailleur ne peut exiger la remise en état des lieux dans leur état primitif.",
  "2I2": "Oui, le Bailleur peut demander la remise en état initial au départ du Preneur en fin de bail.",
  "2J2": "null",
  "2K2": "Oui, droit de préemption en cas de vente des locaux loués.",
  "2L2": "Oui, clause de non-concurrence pesant sur le Bailleur.",
  "2M2": "null",
  "2N2": "null",
  "2O2": "null",
  "2P2": "null",
  "2Q2": "Oui, clause résolutoire présente.",
  "0X2": "Le bail commercial est conclu pour une durée de neuf ans, avec des conditions spécifiques concernant la sous-location et la cession, ainsi qu'une clause résolutoire en cas de non-paiement des loyers."
}
